<?xml version="1.0" encoding="UTF-8" standalone="yes"?>
<AssignMessage async="false" continueOnError="false" enabled="true" name="AM-create-ping-response">
    <DisplayName>AM-create ping response</DisplayName>
    <Properties/>
    <Set>
        <Payload contentType="application/json" variablePrefix="@" variableSuffix="#">{"response":"PONG"}</Payload>
    </Set>
    <IgnoreUnresolvedVariables>true</IgnoreUnresolvedVariables>
    <AssignTo createNew="false" transport="http" type="request"/>
</AssignMessage>